[{"jydm":"515083","jymc":"分捡数据查询                        ","xh":0,"input_screens":[{"hmdm":"5150830","zds":[{"zdxh":5,"zdbt":"交换日期","sjbm":"ExchgDate","zdcd":10,"xssx":"670","sjlx":"3","zdlx":"1","czfs":"0","xxdm":null,"qsh":6,"qsl":31},{"zdxh":10,"zdbt":"交换场次","sjbm":"ExchgPSeq","zdcd":1,"xssx":"670","sjlx":"0","zdlx":"1","czfs":"0","xxdm":null,"qsh":8,"qsl":31}]}]},{"jydm":"515083","jymc":"分捡数据查询                        ","xh":1,"input_screens":[{"hmdm":"5150830","zds":[{"zdxh":5,"zdbt":"交换日期","sjbm":"ExchgDate","zdcd":10,"xssx":"670","sjlx":"3","zdlx":"1","czfs":"0","xxdm":null,"qsh":6,"qsl":31},{"zdxh":10,"zdbt":"交换场次","sjbm":"ExchgPSeq","zdcd":1,"xssx":"670","sjlx":"0","zdlx":"1","czfs":"0","xxdm":null,"qsh":8,"qsl":31}]}]}]